README.md
setup.py
links_pydriver/__init__.py
links_pydriver.egg-info/PKG-INFO
links_pydriver.egg-info/SOURCES.txt
links_pydriver.egg-info/dependency_links.txt
links_pydriver.egg-info/not-zip-safe
links_pydriver.egg-info/top_level.txt
links_pydriver/connection/__init__.py
links_pydriver/connection/db_utils.py
links_pydriver/example/ExampleSaveData.py
links_pydriver/example/__init__.py
links_pydriver/marshaler/DriverMarshaler.py
links_pydriver/marshaler/__init__.py
links_pydriver/model/Entity.py
links_pydriver/model/Experiment.py
links_pydriver/model/Relation.py
links_pydriver/model/Snapshot.py
links_pydriver/model/__init__.py
links_pydriver/tests/__init__.py
links_pydriver/tests/test_marshaler.py