Metadata-Version: 1.0
Name: links-pydriver
Version: 0.4
Summary: A python driver for Links
Home-page: https://github.com/tanguyesteoule/links_pydriver
Author: Tanguy Esteoule
Author-email: tanguy.esteoule@gmail.com
License: MIT
Platform: UNKNOWN
